gltransliter/__init__.py
gltransliter/transliter.py
glagolitic_transliter-1.0.dist-info/LICENSE
glagolitic_transliter-1.0.dist-info/METADATA
glagolitic_transliter-1.0.dist-info/WHEEL
glagolitic_transliter-1.0.dist-info/top_level.txt
glagolitic_transliter-1.0.dist-info/RECORD
