Metadata-Version: 2.1
Name: glagolitic-transliter
Version: 1.0
Summary: Простой транслитератор кириллицы в глаголицу.
Home-page: https://github.com/IlhomBahoraliev/glagolitic-translit
Author: IlhomBahoraliev
Author-email: bahoralievdev@yandex.com
License: UNKNOWN
Platform: UNKNOWN
Classifier: Programming Language :: Python :: 3
Classifier: License :: OSI Approved :: MIT License
Classifier: Operating System :: OS Independent
Requires-Python: >=3.6
